pagnetwork/__init__.py
pagnetwork/paguaga_network.py
pagnetwork-0.0.2.dist-info/LICENSE.txt
pagnetwork-0.0.2.dist-info/METADATA
pagnetwork-0.0.2.dist-info/WHEEL
pagnetwork-0.0.2.dist-info/top_level.txt
pagnetwork-0.0.2.dist-info/RECORD
