Metadata-Version: 2.1
Name: pagnetwork
Version: 0.0.2
Summary: Bayesian Network
Home-page: https://github.com/MGonza20/Lab2_AI
Download-URL: https://github.com/MGonza20/Lab2_AI/archive/refs/tags/0.0.2.tar.gz
Author: Sara Paguaga
Author-email: sara.paguaga@gmail.com
License: MIT
Keywords: pypi,probability,bayes
Classifier: Development Status :: 3 - Alpha
Classifier: Intended Audience :: Developers
Classifier: Topic :: Software Development :: Documentation
Classifier: License :: OSI Approved :: MIT License
Classifier: Programming Language :: Python :: 3
Classifier: Programming Language :: Python :: 3.7
Classifier: Programming Language :: Python :: 3.8
Classifier: Programming Language :: Python :: 3.9
License-File: LICENSE.txt
Requires-Dist: requests
